LICENSE.txt
setup.py
CUITDuoYuan/__init__.py
CUITDuoYuan/main.py
CUITDuoYuan.egg-info/PKG-INFO
CUITDuoYuan.egg-info/SOURCES.txt
CUITDuoYuan.egg-info/dependency_links.txt
CUITDuoYuan.egg-info/top_level.txt