Metadata-Version: 2.1
Name: CUITDuoYuan
Version: 0.0.4
Summary: CUIT duo yuan kao shi da an
Author: zuoShiYun
Author-email: 2818252801@qq.com
Classifier: Programming Language :: Python :: 3
Classifier: License :: OSI Approved :: MIT License
Classifier: Operating System :: OS Independent
Requires-Python: >=3.0
License-File: LICENSE.txt
